homebase/__init__.py
homebase/homebase.py
homebase-1.0.1.dist-info/METADATA
homebase-1.0.1.dist-info/RECORD
homebase-1.0.1.dist-info/WHEEL
homebase-1.0.1.dist-info/top_level.txt
test/__init__.py
test/test_homebase.py
