Metadata-Version: 1.1
Name: homebase
Version: 1.0.1
Summary: A platform independent API for paths in which applications can write data.
Home-page: https://github.com/dwavesystems/homebase
Author: D-Wave Systems Inc.
Author-email: oshklarsky@dwavesys.com
License: Apache 2.0
Download-URL: https://github.com/dwavesystems/homebase/archive/1.0.1.tar.gz
Platform: UNKNOWN
